tkadw_material/__init__.py
tkadw_material/btn.py
tkadw_material/editor.py
tkadw_material/element.py
tkadw_material/input.py
tkadw_material/style.py
tkadw_material/window.py
tkadw_material-0.0.1a3.dist-info/METADATA
tkadw_material-0.0.1a3.dist-info/WHEEL
tkadw_material-0.0.1a3.dist-info/RECORD
